moonstream/__init__.py
moonstream/client.py
moonstream/data.py
moonstream/exceptions.py
moonstream/settings.py
moonstream/test_client.py
moonstream/version.py
moonstream/aws/__init__.py
moonstream/aws/bucket.py
moonstream-0.1.2.dist-info/METADATA
moonstream-0.1.2.dist-info/WHEEL
moonstream-0.1.2.dist-info/top_level.txt
moonstream-0.1.2.dist-info/RECORD
