Metadata-Version: 2.1
Name: moonstream
Version: 0.1.2
Summary: Moonstream: Open source blockchain analytics
Home-page: https://github.com/bugout-dev/moonstream
Author: Moonstream
Author-email: engineering@moonstream.to
Classifier: Development Status :: 3 - Alpha
Classifier: Programming Language :: Python
Classifier: License :: OSI Approved :: Apache Software License
Classifier: Topic :: Software Development :: Libraries
Requires-Dist: requests
Requires-Dist: pydantic
Requires-Dist: dataclasses; python_version == "3.6"
Provides-Extra: aws
Requires-Dist: boto3; extra == "aws"
Provides-Extra: dev
Requires-Dist: black; extra == "dev"
Requires-Dist: mypy; extra == "dev"
Requires-Dist: isort; extra == "dev"
Requires-Dist: wheel; extra == "dev"
Requires-Dist: types-requests; extra == "dev"
Requires-Dist: types-dataclasses; extra == "dev"
Provides-Extra: distribute
Requires-Dist: build; extra == "distribute"
Requires-Dist: twine; extra == "distribute"
